Metadata-Version: 2.4
Name: deeporigin
Version: 4.5.3
Summary: Deep Origin Python client
Author-email: Deep Origin <support@deeporigin.com>
Classifier: Environment :: Console
Classifier: Intended Audience :: End Users/Desktop
Classifier: Natural Language :: English
Classifier: Programming Language :: Python :: 3
Classifier: Topic :: Utilities
Requires-Python: <3.14,>=3.11
License-File: LICENSE.txt
Requires-Dist: beartype
Requires-Dist: cryptography
Requires-Dist: httpx
Requires-Dist: pyjwt
Requires-Dist: tqdm
Provides-Extra: core
Requires-Dist: humanize; extra == "core"
Requires-Dist: jinja2; extra == "core"
Requires-Dist: more-itertools; extra == "core"
Requires-Dist: nest_asyncio; extra == "core"
Requires-Dist: packaging; extra == "core"
Requires-Dist: pandas; extra == "core"
Requires-Dist: tabulate; extra == "core"
Provides-Extra: lint
Requires-Dist: ruff; extra == "lint"
Provides-Extra: test
Requires-Dist: pytest; extra == "test"
Requires-Dist: parameterized; extra == "test"
Requires-Dist: coverage; extra == "test"
Requires-Dist: interrogate; extra == "test"
Requires-Dist: pytest-xdist; extra == "test"
Requires-Dist: pytest-markdown-docs; extra == "test"
Requires-Dist: pytest-dependency; extra == "test"
Requires-Dist: fastapi; extra == "test"
Requires-Dist: uvicorn[standard]; extra == "test"
Provides-Extra: dev
Requires-Dist: ipykernel; extra == "dev"
Requires-Dist: jupyter-black; extra == "dev"
Provides-Extra: docs
Requires-Dist: mkdocs; extra == "docs"
Requires-Dist: mkdocs-material-extensions; extra == "docs"
Requires-Dist: mkdocs-material>=8.2.0; extra == "docs"
Requires-Dist: mkdocstrings; extra == "docs"
Requires-Dist: mkdocstrings-python; extra == "docs"
Requires-Dist: black; extra == "docs"
Requires-Dist: click==8.2.1; extra == "docs"
Requires-Dist: python-dotenv; extra == "docs"
Requires-Dist: nbconvert; extra == "docs"
Requires-Dist: ipykernel; extra == "docs"
Provides-Extra: plots
Requires-Dist: bokeh; extra == "plots"
Provides-Extra: tools
Requires-Dist: rdkit==2025.9.1; extra == "tools"
Requires-Dist: deeporigin-molstar==0.1.1; extra == "tools"
Requires-Dist: biotite; extra == "tools"
Requires-Dist: biopython; extra == "tools"
Requires-Dist: rcsb-api>=1.1.4; extra == "tools"
Dynamic: license-file
